.coveragerc
LICENSE
MANIFEST.in
Makefile
README.rst
make.bat
requirements.txt
setup.cfg
setup.py
tox.ini
CWR_API.egg-info/PKG-INFO
CWR_API.egg-info/SOURCES.txt
CWR_API.egg-info/dependency_links.txt
CWR_API.egg-info/requires.txt
CWR_API.egg-info/top_level.txt
config_cwr/__init__.py
config_cwr/accessor.py
config_cwr/acknowledge_config_example.yml
config_cwr/default_values.yml
config_cwr/field_config_common.yml
config_cwr/field_config_filename.yml
config_cwr/field_config_table.yml
config_cwr/group_config_common.cml
config_cwr/record_config_common.cml
config_cwr/record_config_filename.cml
config_cwr/transaction_config_common.cml
cwr/__init__.py
cwr/acknowledgement.py
cwr/agreement.py
cwr/file.py
cwr/group.py
cwr/info.py
cwr/interested_party.py
cwr/non_roman_alphabet.py
cwr/other.py
cwr/record.py
cwr/table_value.py
cwr/transmission.py
cwr/work.py
cwr/acknowledge/__init__.py
cwr/acknowledge/file.py
cwr/grammar/__init__.py
cwr/grammar/factory/__init__.py
cwr/grammar/factory/adapter.py
cwr/grammar/factory/config.py
cwr/grammar/factory/decorator.py
cwr/grammar/factory/rule.py
cwr/grammar/field/__init__.py
cwr/grammar/field/basic.py
cwr/grammar/field/filename.py
cwr/grammar/field/record.py
cwr/grammar/field/special.py
cwr/grammar/field/table.py
cwr/parser/__init__.py
cwr/parser/decoder/__init__.py
cwr/parser/decoder/common.py
cwr/parser/decoder/cwrjson.py
cwr/parser/decoder/dictionary.py
cwr/parser/decoder/file.py
cwr/parser/encoder/__init__.py
cwr/parser/encoder/common.py
cwr/parser/encoder/cwrjson.py
cwr/parser/encoder/dictionary.py
cwr/parser/encoder/file.py
cwr/parser/encoder/standart/__init__.py
cwr/parser/encoder/standart/field.py
cwr/parser/encoder/standart/record.py
cwr/utils/__init__.py
cwr/utils/printer.py
cwr/validation/__init__.py
cwr/validation/common.py
cwr/validation/record.py
cwr/validation/transaction.py
data_cwr/__init__.py
data_cwr/accessor.py
data_cwr/cwr_agreement_role_code.csv
data_cwr/cwr_agreement_type.csv
data_cwr/cwr_character_set.csv
data_cwr/cwr_composite_type.csv
data_cwr/cwr_excerpt_type.csv
data_cwr/cwr_files_manufacture_clause.csv
data_cwr/cwr_inclusion_exclusion_indicator.csv
