Metadata-Version: 1.1
Name: CWR-API
Version: 0.0.40
Summary: API library for the CWR standard format
Home-page: https://github.com/weso/CWR-DataApi
Author: WESO
Author-email: weso@weso.es
License: MIT
Download-URL: https://pypi.python.org/pypi/CWR-API
Keywords: CWR,commonworks,api,CISAC,parser
Platform: any
Classifier: License :: OSI Approved :: MIT License
Classifier: Development Status :: 3 - Alpha
Classifier: Intended Audience :: Developers
Classifier: Operating System :: OS Independent
Classifier: Programming Language :: Python
Classifier: Programming Language :: Python :: 3
Classifier: Programming Language :: Python :: 3.3
Classifier: Programming Language :: Python :: 3.4
Classifier: Programming Language :: Python :: 3.5
Classifier: Topic :: Software Development :: Libraries :: Python Modules
